tuxparse/__init__.py
tuxparse/__main__.py
tuxparse/boot_test_parser.py
tuxparse/build_parser.py
tuxparse/test_parser.py
tuxparse/lib/base_log_parser.py
tuxparse-0.6.0.dist-info/entry_points.txt
tuxparse-0.6.0.dist-info/LICENSE
tuxparse-0.6.0.dist-info/WHEEL
tuxparse-0.6.0.dist-info/METADATA
tuxparse-0.6.0.dist-info/RECORD
