Metadata-Version: 2.1
Name: tuxparse
Version: 0.6.0
Summary: Command line tool for parsing build and boot/test logs
Home-page: https://gitlab.com/Linaro/lkft/tuxparse
Author: Anders Roxell
Author-email: anders.roxell@linaro.org
Requires-Python: >=3.6
Classifier: License :: OSI Approved :: MIT License
Requires-Dist: PyYAML
